Metadata-Version: 2.1
Name: weekdaytime
Version: 0.0.9
Summary: Python library that models available periods in a week
Home-page: https://github.com/AaronTHCheung/weekdaytime
Author: Aaron Cheung
License: MIT
Platform: UNKNOWN
Requires-Python: >=3.6
License-File: LICENSE
